gtfo/__init__.py
gtfo/_cli.py
gtfo/_version.py
gtfo/core.py
gtfo/tests/__init__.py
gtfo/tests/test_core.py
gtfo-0.3.0.dist-info/DESCRIPTION.rst
gtfo-0.3.0.dist-info/METADATA
gtfo-0.3.0.dist-info/RECORD
gtfo-0.3.0.dist-info/WHEEL
gtfo-0.3.0.dist-info/entry_points.txt
gtfo-0.3.0.dist-info/metadata.json
gtfo-0.3.0.dist-info/top_level.txt
