Metadata-Version: 2.0
Name: gtfo
Version: 0.3.0
Summary: Flight search... please.
Home-page: https://github.com/Julian/gtfo
Author: Julian Berman
Author-email: Julian@GrayVines.com
License: UNKNOWN
Platform: UNKNOWN
Classifier: Development Status :: 3 - Alpha
Classifier: Operating System :: OS Independent
Classifier: Programming Language :: Python
Classifier: License :: OSI Approved :: MIT License
Classifier: Programming Language :: Python :: 2.7
Classifier: Programming Language :: Python :: 3.6
Classifier: Programming Language :: Python :: 2
Classifier: Programming Language :: Python :: 3
Classifier: Programming Language :: Python :: Implementation :: CPython
Classifier: Programming Language :: Python :: Implementation :: PyPy
Requires-Dist: attrs
Requires-Dist: click
Requires-Dist: hyperlink
Requires-Dist: pyrsistent
